nonebot_plugin_miao/__init__.py
nonebot_plugin_miao/config.py
nonebot_plugin_miao-1.1.0.dist-info/LICENSE
nonebot_plugin_miao-1.1.0.dist-info/METADATA
nonebot_plugin_miao-1.1.0.dist-info/WHEEL
nonebot_plugin_miao-1.1.0.dist-info/RECORD
