Metadata-Version: 2.1
Name: nonebot-plugin-miao
Version: 1.1.0
Summary: Nonebot2 plugin to make your bot talk weird.
Home-page: https://github.com/CMHopeSunshine/nonebot-plugin-miao
License: AGPL
Keywords: nonebot2
Author: CMHopeSunshine
Author-email: 277073121@qq.com
Requires-Python: >=3.8,<4.0
Classifier: License :: Other/Proprietary License
Classifier: Programming Language :: Python :: 3
Classifier: Programming Language :: Python :: 3.8
Classifier: Programming Language :: Python :: 3.9
Classifier: Programming Language :: Python :: 3.10
Classifier: Programming Language :: Python :: 3.11
Requires-Dist: nonebot2 (>=2.0.0-rc.2,<3.0.0)
